Metadata-Version: 1.1
Name: smallworld
Version: 0.0.1
Summary: Generate modified small-world networks and compare with theoretical predictions.
Home-page: https://github.com/benmaier/pysmallworld
Author: Benjamin F. Maier
Author-email: bfmaier@physik.hu-berlin.de
License: MIT
Platform: UNKNOWN
Classifier: Programming Language :: Python :: 3
